MANIFEST.in
README.rst
setup.py
src/qdj/__init__.py
src/qdj/cmd.py
src/qdj/projecttemplate.py
src/qdj.egg-info/PKG-INFO
src/qdj.egg-info/SOURCES.txt
src/qdj.egg-info/dependency_links.txt
src/qdj.egg-info/entry_points.txt
src/qdj.egg-info/requires.txt
src/qdj.egg-info/top_level.txt