Metadata-Version: 1.0
Name: qdj
Version: 0.4
Summary: QDJ is 'django-admin.py startproject', but with your own project templates. The project starter for obsessives with deadlines.
Home-page: https://github.com/nathforge/qdj
Author: Nathan Reynolds
Author-email: email@nreynolds.co.uk
License: UNKNOWN
Platform: UNKNOWN
